{
    "version": "3.1.1",
    "description": "Very simple server for the Gemini hypertext protocol",
    "homepage": "https://github.com/mbrubeck/agate",
    "license": "Apache-2.0",
    "architecture": {
        "64bit": {
            "url": "https://github.com/mbrubeck/agate/releases/download/v3.1.1/agate.x86_64-pc-windows-msvc.zip",
            "hash": "48cb65dcd00dd53010ef352ea4ff59726f5fd9c4aca1db16a9644d8ef4be75b4"
        }
    },
    "bin": "agate.exe",
    "checkver": "github",
    "autoupdate": {
        "architecture": {
            "64bit": {
                "url": "https://github.com/mbrubeck/agate/releases/download/v$version/agate.x86_64-pc-windows-msvc.zip"
            }
        }
    }
}
