{
    "version": "1.0.5",
    "description": "World's fastest immutable database - server",
    "homepage": "https://www.codenotary.com/technologies/immudb/",
    "license": "Apache-2.0",
    "architecture": {
        "64bit": {
            "url": "https://github.com/vchain-us/immudb/releases/download/v1.0.5/immudb-v1.0.5-windows-amd64.exe#/immudb.exe",
            "hash": "b37c12b0120a85bb732bd835e60dff83ccd0313d9cdf09a045e7d57f77a9f496"
        }
    },
    "bin": "immudb.exe",
    "checkver": {
        "github": "https://github.com/codenotary/immudb"
    },
    "autoupdate": {
        "architecture": {
            "64bit": {
                "url": "https://github.com/vchain-us/immudb/releases/download/v$version/immudb-v$version-windows-amd64.exe#/immudb.exe"
            }
        }
    }
}
